<?xml version="1.0" encoding="UTF-8"?>
<DocSetNodes version="1.0">
  <TOC>
    <Node>
      <Name>Root</Name>
      <Path>index.html</Path>
      <Subnodes>
       <Node>
        <Name>Rehab Tracker</Name>
        <Path>index.html</Path>
        <Subnodes>
         <Node>
          <Name>Overview</Name>
          <Path>index.html</Path>
          <Anchor>Overview</Anchor>
         </Node>
         <Node>
          <Name>Directory</Name>
          <Path>index.html</Path>
          <Anchor>Folder</Anchor>
         </Node>
         <Node>
          <Name>Install Arduino</Name>
          <Path>install_arduino.html</Path>
          <Subnodes>
           <Node>
            <Name>Install</Name>
            <Path>install_arduino.html</Path>
            <Anchor>Install</Anchor>
           </Node>
           <Node>
            <Name>Port Not Found</Name>
            <Path>install_arduino.html</Path>
            <Anchor>recovery</Anchor>
           </Node>
          </Subnodes>
         </Node>
        </Subnodes>
       </Node>
       <Node>
        <Name>Files</Name>
        <Path>files.html</Path>
        <Subnodes>
         <Node>
          <Name>File List</Name>
          <Path>files.html</Path>
          <Subnodes>
           <Node>
            <Name>Hardware</Name>
            <Path>dir_6cc751a9e685a986d41d35de353de328.html</Path>
            <Subnodes>
             <Node>
              <Name>Arduino</Name>
              <Path>dir_cd7e1643b13ae7e093711e356fbfb157.html</Path>
              <Subnodes>
               <Node>
                <Name>Arduino.ino</Name>
                <Path>_arduino_8ino.html</Path>
                <Subnodes>
                 <Node>
                  <Name>ArrayAdd</Name>
                  <Path>_arduino_8ino.html</Path>
                  <Anchor>a1c6f602edd594562f9cb1605df25d53f</Anchor>
                 </Node>
                 <Node>
                  <Name>ButtonInterrupt</Name>
                  <Path>_arduino_8ino.html</Path>
                  <Anchor>a52573902bb826815aa77a3d47254c860</Anchor>
                 </Node>
                 <Node>
                  <Name>initialize</Name>
                  <Path>_arduino_8ino.html</Path>
                  <Anchor>a25a40b6614565f755233080a384c35f1</Anchor>
                 </Node>
                 <Node>
                  <Name>IntensityMap</Name>
                  <Path>_arduino_8ino.html</Path>
                  <Anchor>a992780a393bb17ed9c6f96a1822808fa</Anchor>
                 </Node>
                 <Node>
                  <Name>loop</Name>
                  <Path>_arduino_8ino.html</Path>
                  <Anchor>afe461d27b9c48d5921c00d521181f12f</Anchor>
                 </Node>
                 <Node>
                  <Name>outputtingToApp</Name>
                  <Path>_arduino_8ino.html</Path>
                  <Anchor>a752007f4f4b1f240f9c0877fb1999e7e</Anchor>
                 </Node>
                 <Node>
                  <Name>setup</Name>
                  <Path>_arduino_8ino.html</Path>
                  <Anchor>a4fc01d736fe50cf5b977f755b675f11d</Anchor>
                 </Node>
                 <Node>
                  <Name>WriteStorage</Name>
                  <Path>_arduino_8ino.html</Path>
                  <Anchor>ae938d2541a15a3cec4e6c47b92795112</Anchor>
                 </Node>
                 <Node>
                  <Name>ant1</Name>
                  <Path>_arduino_8ino.html</Path>
                  <Anchor>a07d4d802477900880df44dd189b7b92e</Anchor>
                 </Node>
                 <Node>
                  <Name>ant2</Name>
                  <Path>_arduino_8ino.html</Path>
                  <Anchor>ab01aec0e5c5f20c12efaa091fde8ecb7</Anchor>
                 </Node>
                 <Node>
                  <Name>arrayAvg1</Name>
                  <Path>_arduino_8ino.html</Path>
                  <Anchor>ab840871d2722c85dd0a8037edf271e17</Anchor>
                 </Node>
                 <Node>
                  <Name>arrayAvg2</Name>
                  <Path>_arduino_8ino.html</Path>
                  <Anchor>acbb53c895a2a34e4fbe2cd464c25c801</Anchor>
                 </Node>
                 <Node>
                  <Name>arrayTot1</Name>
                  <Path>_arduino_8ino.html</Path>
                  <Anchor>aa0a6a9d6a73aba16cf53f2540c7dbe7f</Anchor>
                 </Node>
                 <Node>
                  <Name>arrayTot2</Name>
                  <Path>_arduino_8ino.html</Path>
                  <Anchor>aab910fbd19bb81b4274d95e0c3cf8d2d</Anchor>
                 </Node>
                 <Node>
                  <Name>endTime</Name>
                  <Path>_arduino_8ino.html</Path>
                  <Anchor>a22ab9604e2a95f2750f1418182f6ec4a</Anchor>
                 </Node>
                 <Node>
                  <Name>maxVal1</Name>
                  <Path>_arduino_8ino.html</Path>
                  <Anchor>acda812774d5830457137b08a98b6ac61</Anchor>
                 </Node>
                 <Node>
                  <Name>maxVal2</Name>
                  <Path>_arduino_8ino.html</Path>
                  <Anchor>a96ede0a9e95ff51aaee48b56d0af3490</Anchor>
                 </Node>
                 <Node>
                  <Name>next1</Name>
                  <Path>_arduino_8ino.html</Path>
                  <Anchor>ac512d0df33295e846409ac0812214dd7</Anchor>
                 </Node>
                 <Node>
                  <Name>next2</Name>
                  <Path>_arduino_8ino.html</Path>
                  <Anchor>a753ca731edc348857cfd4c39f2bfd2a7</Anchor>
                 </Node>
                 <Node>
                  <Name>now</Name>
                  <Path>_arduino_8ino.html</Path>
                  <Anchor>ac023874b2154eac7297a7575008605fe</Anchor>
                 </Node>
                 <Node>
                  <Name>rtc</Name>
                  <Path>_arduino_8ino.html</Path>
                  <Anchor>a7715afc6e8732f6f936183f5c0d76167</Anchor>
                 </Node>
                 <Node>
                  <Name>sampleNum1</Name>
                  <Path>_arduino_8ino.html</Path>
                  <Anchor>a2d71fd2804a6e570e718627de51e2dbb</Anchor>
                 </Node>
                 <Node>
                  <Name>sampleNum2</Name>
                  <Path>_arduino_8ino.html</Path>
                  <Anchor>a8b3f936086a2900e2df11ea748d57c4b</Anchor>
                 </Node>
                 <Node>
                  <Name>sendFlag</Name>
                  <Path>_arduino_8ino.html</Path>
                  <Anchor>a9ad9aa3998cae3413fd994c2d26d4e98</Anchor>
                 </Node>
                 <Node>
                  <Name>sessionComp</Name>
                  <Path>_arduino_8ino.html</Path>
                  <Anchor>aa2bfc79870709d14006df2eb36155532</Anchor>
                 </Node>
                 <Node>
                  <Name>sessionCount</Name>
                  <Path>_arduino_8ino.html</Path>
                  <Anchor>a803d6b06241ded9831427552153f9201</Anchor>
                 </Node>
                 <Node>
                  <Name>startFlag</Name>
                  <Path>_arduino_8ino.html</Path>
                  <Anchor>a3668a26ea96075b554b79c85b71a9703</Anchor>
                 </Node>
                 <Node>
                  <Name>startTime</Name>
                  <Path>_arduino_8ino.html</Path>
                  <Anchor>a8ad49a66e91d8658c5f1f7dbcbcbbd2f</Anchor>
                 </Node>
                 <Node>
                  <Name>testMode</Name>
                  <Path>_arduino_8ino.html</Path>
                  <Anchor>a8966364542f53bd7cefbc07cb646234a</Anchor>
                 </Node>
                </Subnodes>
               </Node>
              </Subnodes>
             </Node>
            </Subnodes>
           </Node>
          </Subnodes>
         </Node>
         <Node>
          <Name>File Members</Name>
          <Path>globals.html</Path>
          <Subnodes>
           <Node>
            <Name>All</Name>
            <Path>globals.html</Path>
           </Node>
           <Node>
            <Name>Functions</Name>
            <Path>globals_func.html</Path>
           </Node>
           <Node>
            <Name>Variables</Name>
            <Path>globals_vars.html</Path>
           </Node>
          </Subnodes>
         </Node>
        </Subnodes>
       </Node>
      </Subnodes>
    </Node>
  </TOC>
</DocSetNodes>
